cwatch/__init__.py
cwatch/collector.py
cwatch/cw.py
cwatch/data_structures.py
cwatch/email_sender.py
cwatch/reporters.py
cwatch-0.7.16.dist-info/METADATA
cwatch-0.7.16.dist-info/WHEEL
cwatch-0.7.16.dist-info/entry_points.txt
cwatch-0.7.16.dist-info/licenses/LICENSE
cwatch-0.7.16.dist-info/RECORD
