Metadata-Version: 2.4
Name: cwatch
Version: 0.7.16
Summary: Monitors and generates a report for changes in reports from Cyberbro
Project-URL: Homepage, https://github.com/reuteras/cwatch
Project-URL: Issues, https://github.com/reuteras/cwatch/issues
Author-email: Peter Reuterås <peter@reuteras.net>
License: MIT
License-File: LICENSE
Classifier: Operating System :: OS Independent
Classifier: Programming Language :: Python :: 3
Requires-Python: >=3.11
Requires-Dist: httpx>=0.28.1
Requires-Dist: jsondiff>=2.2.1
